decord/logging.py
decord/libdecord.so
decord/av_reader.py
decord/_api_internal.py
decord/audio_reader.py
decord/video_loader.py
decord/__init__.py
decord/video_reader.py
decord/base.py
decord/ndarray.py
decord/_ffi/libinfo.py
decord/_ffi/__init__.py
decord/_ffi/base.py
decord/_ffi/ndarray.py
decord/_ffi/runtime_ctypes.py
decord/_ffi/function.py
decord/_ffi/_ctypes/__init__.py
decord/_ffi/_ctypes/types.py
decord/_ffi/_ctypes/ndarray.py
decord/_ffi/_ctypes/function.py
decord/_ffi/_cy3/__init__.py
decord/_ffi/_cy2/__init__.py
decord/bridge/tvm.py
decord/bridge/mxnet.py
decord/bridge/__init__.py
decord/bridge/utils.py
decord/bridge/torchdl.py
decord/bridge/tf.py
decord/function/__init__.py
decord/function/base.py
decord/data/__init__.py
decord/data/base_action.py
decord/data/dataloader.py
decord/data/kinetics/kinetics400_action.py
decord/data/kinetics/__init__.py
decord/data/transforms/action.py
decord/data/transforms/__init__.py
decord-0.6.0.dist-info/METADATA
decord-0.6.0.dist-info/RECORD
decord-0.6.0.dist-info/top_level.txt
decord-0.6.0.dist-info/WHEEL
decord.libs/libx264-555fb44a.so.164
decord.libs/libavcodec-bc50294c.so.58.35.100
decord.libs/libxcb-77222338.so.1.1.0
decord.libs/libbz2-13e8c345.so.1.0.4
decord.libs/libpostproc-88b722f8.so.55.3.100
decord.libs/libvpx-5769b0ce.so.6.4.0
decord.libs/libXau-b2e5323c.so.6.0.0
decord.libs/libxcb-shm-7ffb2544.so.0.0.0
decord.libs/libz-eb09ad1d.so.1.2.3
decord.libs/libavutil-2b26904a.so.56.22.100
decord.libs/libavformat-8b46ea57.so.58.20.100
decord.libs/libxcb-xfixes-6523fc53.so.0.0.0
decord.libs/libxcb-shape-893f3868.so.0.0.0
decord.libs/libswscale-8e37dcfd.so.5.3.100
decord.libs/libswresample-230d9f46.so.3.3.100
decord.libs/libavdevice-bf61e037.so.58.5.100
decord.libs/libavfilter-1e2243e2.so.7.40.101
